README.md
pyproject.toml
setup.py
src/how/__init__.py
src/how/__main__.py
src/how/cli.py
src/how/constants.py
src/how/how_agent/__init__.py
src/how/how_agent/agent.py
src/how/utils/__init__.py
src/how/utils/config_utils.py
src/how/utils/ollama_utils.py
src/how/utils/os_utils.py
src/how2_shell_assistant.egg-info/PKG-INFO
src/how2_shell_assistant.egg-info/SOURCES.txt
src/how2_shell_assistant.egg-info/dependency_links.txt
src/how2_shell_assistant.egg-info/entry_points.txt
src/how2_shell_assistant.egg-info/not-zip-safe
src/how2_shell_assistant.egg-info/requires.txt
src/how2_shell_assistant.egg-info/top_level.txt