Metadata-Version: 2.4
Name: how2-shell-assistant
Version: 0.1.1
Summary: `how2` is a command-line tool Powered by Large Language Models (LLMs), it translates your natural language questions into executable shell commands.
Home-page: https://github.com/DanHUMassMed/how2.git
Author: Dan Higgins
Author-email: daniel.higgins@gatech.edu
License: MIT
Requires-Python: >=3.9
Requires-Dist: ollama==0.6.0
Requires-Dist: pyperclip==1.11.0
Requires-Dist: psutil==7.1.3
Dynamic: author
Dynamic: author-email
Dynamic: description
Dynamic: description-content-type
Dynamic: home-page
Dynamic: license
Dynamic: requires-dist
Dynamic: requires-python
Dynamic: summary
